altk/__init__.py
altk/build_time/__init__.py
altk/build_time/test_case_generation_toolkit/__init__.py
altk/build_time/test_case_generation_toolkit/core/__init__.py
altk/build_time/test_case_generation_toolkit/core/config.py
altk/build_time/test_case_generation_toolkit/core/toolkit.py
altk/build_time/test_case_generation_toolkit/src/__init__.py
altk/build_time/test_case_generation_toolkit/src/toolops/__init__.py
altk/build_time/test_case_generation_toolkit/src/toolops/exceptions.py
altk/build_time/test_case_generation_toolkit/src/toolops/enrichment/__init__.py
altk/build_time/test_case_generation_toolkit/src/toolops/enrichment/mcp_cf_tool_enrichment/__init__.py
altk/build_time/test_case_generation_toolkit/src/toolops/enrichment/mcp_cf_tool_enrichment/enrichment.py
altk/build_time/test_case_generation_toolkit/src/toolops/enrichment/mcp_cf_tool_enrichment/prompt_utils.py
altk/build_time/test_case_generation_toolkit/src/toolops/enrichment/mcp_cf_tool_enrichment/conf/llm_config.toml
altk/build_time/test_case_generation_toolkit/src/toolops/enrichment/mcp_cf_tool_enrichment/prompts/tool_description.txt
altk/build_time/test_case_generation_toolkit/src/toolops/enrichment/python_tool_enrichment/__init__.py
altk/build_time/test_case_generation_toolkit/src/toolops/enrichment/python_tool_enrichment/enrichment.py
altk/build_time/test_case_generation_toolkit/src/toolops/enrichment/python_tool_enrichment/enrichment_utils/__init__.py
altk/build_time/test_case_generation_toolkit/src/toolops/enrichment/python_tool_enrichment/enrichment_utils/common/__init__.py
altk/build_time/test_case_generation_toolkit/src/toolops/enrichment/python_tool_enrichment/enrichment_utils/common/utils.py
altk/build_time/test_case_generation_toolkit/src/toolops/enrichment/python_tool_enrichment/enrichment_utils/conf/llm_config.toml
altk/build_time/test_case_generation_toolkit/src/toolops/enrichment/python_tool_enrichment/enrichment_utils/conf/wxo_enrichment_config.yaml
agent_lifecycle_toolkit-0.7.0.dist-info/METADATA
agent_lifecycle_toolkit-0.7.0.dist-info/WHEEL
agent_lifecycle_toolkit-0.7.0.dist-info/licenses/LICENSE
agent_lifecycle_toolkit-0.7.0.dist-info/RECORD
