Metadata-Version: 2.4
Name: agent-lifecycle-toolkit
Version: 0.7.0
Summary: The Agent Lifecycle Toolkit (ALTK) is a library of components to help agent builders improve their agent with minimal integration effort and setup.
Project-URL: homepage, https://altk.ai/
Project-URL: documentation, https://agenttoolkit.github.io/agent-lifecycle-toolkit/
Project-URL: source, https://github.com/AgentToolkit/agent-lifecycle-toolkit
Project-URL: download, https://pypi.org/project/agent-lifecycle-toolkit/#files
Project-URL: tracker, https://github.com/AgentToolkit/agent-lifecycle-toolkit/issues
License-File: LICENSE
Keywords: LLM,NLP,RAG,agent,data,devtools,generation,index,retrieval
Classifier: Topic :: Scientific/Engineering :: Artificial Intelligence
Classifier: Topic :: Software Development :: Libraries :: Application Frameworks
Classifier: Topic :: Software Development :: Libraries :: Python Modules
Requires-Python: >=3.10
Requires-Dist: aiofiles>=24.1.0
Requires-Dist: black>=25.1.0
Requires-Dist: datamodel-code-generator>=0.34.0
Requires-Dist: docstring-parser>=0.16
Requires-Dist: genson>=1.3.0
Requires-Dist: ibm-watsonx-ai>=1.0.0
Requires-Dist: jinja2>=3.1.6
Requires-Dist: jsonschema>=4.0.0
Requires-Dist: langchain-chroma>=0.1.4
Requires-Dist: langchain-community>=0.3.21
Requires-Dist: langchain-core>=0.3.72
Requires-Dist: langchain-huggingface>=0.3.0
Requires-Dist: langchain-text-splitters>=1.0.0
Requires-Dist: langgraph>=0.2.74
Requires-Dist: litellm<2.0.0
Requires-Dist: llm-sandbox[docker,podman]>=0.2.5
Requires-Dist: mellea>=0.0.6
Requires-Dist: nestful-wrapper>=0.1.4
Requires-Dist: nl2flow>=0.1.2
Requires-Dist: nltk>=3.9.1
Requires-Dist: openai>=1.0.0
Requires-Dist: pydantic>=2.0.0
Requires-Dist: pyright>=1.1.406
Requires-Dist: pytest-json-report>=1.5.0
Requires-Dist: pytest>=8.2.1
Requires-Dist: scipy>=1.15.3
Requires-Dist: sentence-transformers>=5.0.0
Requires-Dist: smolagents>=1.21.3
Requires-Dist: starlette>=0.49.1
Requires-Dist: tomli>=2.2.1
Requires-Dist: torch==2.2.2; sys_platform == 'darwin' and platform_machine == 'x86_64'
Requires-Dist: torch>=2.5.1; sys_platform != 'darwin' or platform_machine != 'x86_64'
Requires-Dist: transformers>=4.53.3
Requires-Dist: trl>=0.12.2
Requires-Dist: typing-extensions>=4.0.0
Provides-Extra: build
Requires-Dist: uv~=0.8.22; extra == 'build'
Provides-Extra: docs
Requires-Dist: griffe-inherited-docstrings; extra == 'docs'
Requires-Dist: griffe-pydantic; extra == 'docs'
Requires-Dist: mkdocs-awesome-nav; extra == 'docs'
Requires-Dist: mkdocs-click; extra == 'docs'
Requires-Dist: mkdocs-enumerate-headings-plugin; extra == 'docs'
Requires-Dist: mkdocs-include-markdown-plugin>=7.1.8; extra == 'docs'
Requires-Dist: mkdocs-jupyter; extra == 'docs'
Requires-Dist: mkdocs-material; extra == 'docs'
Requires-Dist: mkdocstrings[python]; extra == 'docs'
Provides-Extra: policy-guard
Requires-Dist: ibm-watsonx-ai>=1.3.28; extra == 'policy-guard'
Requires-Dist: pydantic>=2.0.0; extra == 'policy-guard'
Provides-Extra: post-request
Requires-Dist: aiofiles==24.1.0; extra == 'post-request'
Requires-Dist: black>=25.1.0; extra == 'post-request'
Requires-Dist: docstring-parser>=0.16; extra == 'post-request'
Requires-Dist: jsonschema>=4.0.0; extra == 'post-request'
Requires-Dist: langchain-core>=0.3.72; extra == 'post-request'
Requires-Dist: langchain-ibm>=0.3.15; extra == 'post-request'
Requires-Dist: langchain>=0.3.26; extra == 'post-request'
Requires-Dist: langgraph>=0.2.74; extra == 'post-request'
Requires-Dist: tomli==2.2.1; extra == 'post-request'
Provides-Extra: post-tool-reflection
Requires-Dist: genson>=1.3.0; extra == 'post-tool-reflection'
Requires-Dist: langchain-chroma>=0.1.4; extra == 'post-tool-reflection'
Requires-Dist: langchain-community>=0.3.21; extra == 'post-tool-reflection'
Requires-Dist: langchain-core>=0.3.72; extra == 'post-tool-reflection'
Requires-Dist: langchain-huggingface>=0.3.0; extra == 'post-tool-reflection'
Requires-Dist: langchain-ibm>=0.3.15; extra == 'post-tool-reflection'
Requires-Dist: langchain-openai>=0.3.28; extra == 'post-tool-reflection'
Requires-Dist: llm-sandbox[docker]>=0.2.5; extra == 'post-tool-reflection'
Requires-Dist: pydantic>=2.0.0; extra == 'post-tool-reflection'
Requires-Dist: smolagents>=1.21.3; extra == 'post-tool-reflection'
Provides-Extra: pre-tool-guard
Requires-Dist: datamodel-code-generator>=0.34.0; extra == 'pre-tool-guard'
Requires-Dist: mellea>=0.0.6; extra == 'pre-tool-guard'
Requires-Dist: pydantic>=2.0.0; extra == 'pre-tool-guard'
Requires-Dist: pyright>=1.1.406; extra == 'pre-tool-guard'
Requires-Dist: pytest-json-report>=1.5.0; extra == 'pre-tool-guard'
Requires-Dist: pytest>=8.2.1; extra == 'pre-tool-guard'
Provides-Extra: pre-tool-reflection
Requires-Dist: jinja2>=3.1.6; extra == 'pre-tool-reflection'
Requires-Dist: jsonschema>=4.0.0; extra == 'pre-tool-reflection'
Requires-Dist: nestful-wrapper>=0.1.4; extra == 'pre-tool-reflection'
Requires-Dist: nl2flow>=0.1.2; extra == 'pre-tool-reflection'
Requires-Dist: pydantic>=2.0.0; extra == 'pre-tool-reflection'
Requires-Dist: scipy>=1.15.3; extra == 'pre-tool-reflection'
Requires-Dist: sentence-transformers>=5.0.0; extra == 'pre-tool-reflection'
